<?xml version="1.0" encoding="UTF-8" standalone="no"?>
<Configuration>
  <Targets>
    <Target path="target\Web1.war">
      <CustomBuildInfo additional_classpath="..\..\..\.m2\repository\mysql\mysql-connector-java\5.1.48\mysql-connector-java-5.1.48.jar;..\..\..\.m2\repository\javax\servlet\javax.servlet-api\4.0.1\javax.servlet-api-4.0.1.jar" jdk_path="..\..\..\..\..\Program Files\Eclipse Adoptium\jdk-17.0.7.7-hotspot" jsp_compiler="Default Tomcat JSP Compiler" package_includes="com.journaldev" src_root="src\main\java"/>
      <Exclude>WEB-INF\lib\mysql-connector-java-5.1.48.jar</Exclude>
      <Exclude>WEB-INF\lib\javax.servlet-api-4.0.1.jar</Exclude>
    </Target>
  </Targets>
</Configuration>
